showdf/__init__.py
showdf/main.py
chan127_demo-0.0.4.dist-info/LICENSE
chan127_demo-0.0.4.dist-info/METADATA
chan127_demo-0.0.4.dist-info/WHEEL
chan127_demo-0.0.4.dist-info/entry_points.txt
chan127_demo-0.0.4.dist-info/top_level.txt
chan127_demo-0.0.4.dist-info/RECORD
