Metadata-Version: 2.1
Name: chan127-demo
Version: 0.0.4
Summary: show one row of dataframe
Author: ck
License-File: LICENSE
Requires-Dist: pandas
Requires-Dist: click
